mizuio/__init__.py
mizuio/cleaner.py
mizuio/cli.py
mizuio/utils.py
mizuio/visualizer.py
mizuio-0.1.1.dist-info/licenses/LICENSE
mizuio-0.1.1.dist-info/METADATA
mizuio-0.1.1.dist-info/WHEEL
mizuio-0.1.1.dist-info/entry_points.txt
mizuio-0.1.1.dist-info/top_level.txt
mizuio-0.1.1.dist-info/RECORD
